thu_auth_g4197/__init__.py
thu_auth_g4197/thu_auth.py
thu_auth_g4197-0.0.2.dist-info/METADATA
thu_auth_g4197-0.0.2.dist-info/WHEEL
thu_auth_g4197-0.0.2.dist-info/top_level.txt
thu_auth_g4197-0.0.2.dist-info/RECORD
