Metadata-Version: 2.1
Name: thu_auth_g4197
Version: 0.0.2
Summary: A simple auth function for Tsinghua
Author-email: g4197 <cfhmgh@163.com>
Requires-Dist: requests
Requires-Dist: gmssl
Requires-Dist: binascii
